<?xml version="1.0" encoding="UTF-8"?>
<!DOCTYPE mapper PUBLIC "-//mybatis.org//DTD Mapper 3.0//EN" "http://mybatis.org/dtd/mybatis-3-mapper.dtd">
<mapper namespace="com.glutton.cms.mapping.person.CmsUserMapper">
  <resultMap id="BaseResultMap" type="com.glutton.cms.dao.person.CmsUser">
    <!--
      WARNING - @mbg.generated
      This element is automatically generated by MyBatis Generator, do not modify.
      This element was generated on Fri Jul 26 16:29:37 CST 2019.
    -->
    <id column="user_id" jdbcType="BIGINT" property="userId" />
    <result column="user_name" jdbcType="VARCHAR" property="userName" />
    <result column="user_age" jdbcType="INTEGER" property="userAge" />
    <result column="user_nickname" jdbcType="VARCHAR" property="userNickname" />
    <result column="user_phone" jdbcType="VARCHAR" property="userPhone" />
    <result column="join_date" jdbcType="TIMESTAMP" property="joinDate" />
    <result column="user_email" jdbcType="VARCHAR" property="userEmail" />
  </resultMap>
  <delete id="deleteByPrimaryKey" parameterType="java.lang.Long">
    <!--
      WARNING - @mbg.generated
      This element is automatically generated by MyBatis Generator, do not modify.
      This element was generated on Fri Jul 26 16:29:37 CST 2019.
    -->
    delete from cms_user
    where user_id = #{userId,jdbcType=BIGINT}
  </delete>
  <insert id="insert" parameterType="com.glutton.cms.dao.person.CmsUser">
    <!--
      WARNING - @mbg.generated
      This element is automatically generated by MyBatis Generator, do not modify.
      This element was generated on Fri Jul 26 16:29:37 CST 2019.
    -->
    insert into cms_user (user_id, user_name, user_age, 
      user_nickname, user_phone, join_date, 
      user_email)
    values (#{userId,jdbcType=BIGINT}, #{userName,jdbcType=VARCHAR}, #{userAge,jdbcType=INTEGER}, 
      #{userNickname,jdbcType=VARCHAR}, #{userPhone,jdbcType=VARCHAR}, #{joinDate,jdbcType=TIMESTAMP}, 
      #{userEmail,jdbcType=VARCHAR})
  </insert>
  <update id="updateByPrimaryKey" parameterType="com.glutton.cms.dao.person.CmsUser">
    <!--
      WARNING - @mbg.generated
      This element is automatically generated by MyBatis Generator, do not modify.
      This element was generated on Fri Jul 26 16:29:37 CST 2019.
    -->
    update cms_user
    set user_name = #{userName,jdbcType=VARCHAR},
      user_age = #{userAge,jdbcType=INTEGER},
      user_nickname = #{userNickname,jdbcType=VARCHAR},
      user_phone = #{userPhone,jdbcType=VARCHAR},
      join_date = #{joinDate,jdbcType=TIMESTAMP},
      user_email = #{userEmail,jdbcType=VARCHAR}
    where user_id = #{userId,jdbcType=BIGINT}
  </update>
  <select id="selectByPrimaryKey" parameterType="java.lang.Long" resultMap="BaseResultMap">
    <!--
      WARNING - @mbg.generated
      This element is automatically generated by MyBatis Generator, do not modify.
      This element was generated on Fri Jul 26 16:29:37 CST 2019.
    -->
    select user_id, user_name, user_age, user_nickname, user_phone, join_date, user_email
    from cms_user
    where user_id = #{userId,jdbcType=BIGINT}
  </select>
  <select id="selectAll" resultMap="BaseResultMap">
    <!--
      WARNING - @mbg.generated
      This element is automatically generated by MyBatis Generator, do not modify.
      This element was generated on Fri Jul 26 16:29:37 CST 2019.
    -->
    select user_id, user_name, user_age, user_nickname, user_phone, join_date, user_email
    from cms_user
  </select>
</mapper>